LICENSE
README.md
setup.py
stateen/__init__.py
stateen/core.py
stateen/debugging.py
stateen/hooks.py
stateen/persistence.py
stateen.egg-info/PKG-INFO
stateen.egg-info/SOURCES.txt
stateen.egg-info/dependency_links.txt
stateen.egg-info/entry_points.txt
stateen.egg-info/requires.txt
stateen.egg-info/top_level.txt
tests/__init__.py
tests/run_tests.py
tests/test_core.py
tests/test_debugging.py
tests/test_hooks.py
tests/test_persistence.py