Metadata-Version: 2.4
Name: stateen
Version: 1.0.0
Summary: Minimal state management library similar to React's useState for Python
Home-page: https://github.com/tikipiya/stateen
Author: tikisan
Author-email: s2501082@sendai-nct.jp
Project-URL: Bug Reports, https://github.com/tikipiya/stateen/issues
Project-URL: Source, https://github.com/tikipiya/stateen
Project-URL: Documentation, https://github.com/tikipiya/stateen
Keywords: state management,react,hooks,gui,cli,games,reactive
Classifier: Development Status :: 5 - Production/Stable
Classifier: Intended Audience :: Developers
Classifier: License :: OSI Approved :: MIT License
Classifier: Operating System :: OS Independent
Classifier: Programming Language :: Python :: 3
Classifier: Programming Language :: Python :: 3.8
Classifier: Programming Language :: Python :: 3.9
Classifier: Programming Language :: Python :: 3.10
Classifier: Programming Language :: Python :: 3.11
Classifier: Programming Language :: Python :: 3.12
Classifier: Topic :: Software Development :: Libraries :: Python Modules
Classifier: Topic :: Software Development :: User Interfaces
Requires-Python: >=3.8
License-File: LICENSE
Provides-Extra: dev
Requires-Dist: pytest>=7.0.0; extra == "dev"
Requires-Dist: pytest-cov>=4.0.0; extra == "dev"
Requires-Dist: black>=23.0.0; extra == "dev"
Requires-Dist: flake8>=6.0.0; extra == "dev"
Requires-Dist: mypy>=1.0.0; extra == "dev"
Provides-Extra: gui
Requires-Dist: tkinter; extra == "gui"
Requires-Dist: PyQt5>=5.15.0; extra == "gui"
Requires-Dist: PyQt6>=6.4.0; extra == "gui"
Provides-Extra: async
Requires-Dist: asyncio; extra == "async"
Requires-Dist: aiofiles>=22.0.0; extra == "async"
Dynamic: author
Dynamic: author-email
Dynamic: classifier
Dynamic: description
Dynamic: description-content-type
Dynamic: home-page
Dynamic: keywords
Dynamic: license-file
Dynamic: project-url
Dynamic: provides-extra
Dynamic: requires-python
Dynamic: summary
